setup.py
threatrecon/__init__.py
threatrecon/api.py
threatrecon/query.py
threatrecon/sslv3.py
threatrecon.egg-info/PKG-INFO
threatrecon.egg-info/SOURCES.txt
threatrecon.egg-info/dependency_links.txt
threatrecon.egg-info/requires.txt
threatrecon.egg-info/top_level.txt