Metadata-Version: 1.0
Name: threatrecon
Version: 1.0.3
Summary: Python API module for Wapack Labs ThreatRecon service.
Home-page: UNKNOWN
Author: Wapack Labs
Author-email: chall@wapacklabs.com
License: UNKNOWN
Platform: UNKNOWN
